<Properties StartupConfiguration="{08C9773D-3799-4F73-AFBC-C37FF91CF8C8}|Default">
  <MonoDevelop.Ide.DebuggingService.PinnedWatches />
  <MonoDevelop.Ide.DebuggingService.Breakpoints>
    <BreakpointStore />
  </MonoDevelop.Ide.DebuggingService.Breakpoints>
  <MonoDevelop.Ide.Workspace ActiveConfiguration="Debug" />
  <MonoDevelop.Ide.Workbench ActiveDocument="Program.cs">
    <Files>
      <File FileName="Program.cs" Line="1" Column="29" />
    </Files>
    <Pads>
      <Pad Id="ProjectPad">
        <State name="__root__">
          <Node name="AnimalInheritance" expanded="True">
            <Node name="AnimalInheritance" expanded="True">
              <Node name="Program.cs" selected="True" />
            </Node>
          </Node>
        </State>
      </Pad>
    </Pads>
  </MonoDevelop.Ide.Workbench>
  <MonoDevelop.Ide.ItemProperties.AnimalInheritance PreferredExecutionTarget="MonoDevelop.Default" />
  <MultiItemStartupConfigurations />
</Properties>